{
  "canvas": {
    "version": "2.2.11",
    "width": 2000,
    "height": 2000,
    "scrollTop": 0,
    "scrollLeft": 0,
    "zoomLevel": 1,
    "show": {
      "tableComment": true,
      "columnComment": true,
      "columnDataType": true,
      "columnDefault": true,
      "columnAutoIncrement": false,
      "columnPrimaryKey": true,
      "columnUnique": false,
      "columnNotNull": true,
      "relationship": true
    },
    "database": "MySQL",
    "databaseName": "",
    "canvasType": "ERD",
    "language": "GraphQL",
    "tableCase": "pascalCase",
    "columnCase": "camelCase",
    "highlightTheme": "VS2015",
    "bracketType": "none",
    "setting": {
      "relationshipDataTypeSync": true,
      "relationshipOptimization": false,
      "columnOrder": [
        "columnName",
        "columnDataType",
        "columnNotNull",
        "columnUnique",
        "columnAutoIncrement",
        "columnDefault",
        "columnComment"
      ]
    },
    "pluginSerializationMap": {}
  },
  "table": {
    "tables": [
      {
        "name": "board",
        "comment": "게시판",
        "columns": [
          {
            "name": "id",
            "comment": "auto_increment",
            "dataType": "INT",
            "default": "",
            "option": {
              "autoIncrement": false,
              "primaryKey": true,
              "unique": false,
              "notNull": true
            },
            "ui": {
              "active": false,
              "pk": true,
              "fk": false,
              "pfk": false,
              "widthName": 60,
              "widthComment": 86.10987854003906,
              "widthDataType": 60,
              "widthDefault": 60
            },
            "id": "51b29a7b-e8c7-44b6-8f36-9f024fab3aa3"
          },
          {
            "name": "title",
            "comment": "",
            "dataType": "VARCHAR(255)",
            "default": "",
            "option": {
              "autoIncrement": false,
              "primaryKey": false,
              "unique": false,
              "notNull": true
            },
            "ui": {
              "active": false,
              "pk": false,
              "fk": false,
              "pfk": false,
              "widthName": 60,
              "widthComment": 60,
              "widthDataType": 84.10789489746094,
              "widthDefault": 60
            },
            "id": "d81c32f5-72a8-4cd9-98f8-9682b32161bf"
          },
          {
            "name": "content",
            "comment": "",
            "dataType": "TEXT",
            "default": "",
            "option": {
              "autoIncrement": false,
              "primaryKey": false,
              "unique": false,
              "notNull": true
            },
            "ui": {
              "active": false,
              "pk": false,
              "fk": false,
              "pfk": false,
              "widthName": 60,
              "widthComment": 60,
              "widthDataType": 60,
              "widthDefault": 60
            },
            "id": "0e0625da-b660-434a-b544-6e2b8110ecbb"
          },
          {
            "name": "writer",
            "comment": "",
            "dataType": "VARCHAR(255)",
            "default": "",
            "option": {
              "autoIncrement": false,
              "primaryKey": false,
              "unique": false,
              "notNull": true
            },
            "ui": {
              "active": false,
              "pk": false,
              "fk": false,
              "pfk": false,
              "widthName": 60,
              "widthComment": 60,
              "widthDataType": 84.10789489746094,
              "widthDefault": 60
            },
            "id": "b874ff5f-3192-4d48-b672-a2d0fb46e43e"
          },
          {
            "name": "created_at",
            "comment": "",
            "dataType": "TIMESTAMP",
            "default": "CURRENT_TIMESTAMP",
            "option": {
              "autoIncrement": false,
              "primaryKey": false,
              "unique": false,
              "notNull": false
            },
            "ui": {
              "active": false,
              "pk": false,
              "fk": false,
              "pfk": false,
              "widthName": 60,
              "widthComment": 60,
              "widthDataType": 68.2479248046875,
              "widthDefault": 126.42286682128906
            },
            "id": "17605d50-292a-4ad5-84da-50658c285c71"
          },
          {
            "name": "updated_at",
            "comment": "ON UPDATE CURRENT_TIMESTAMP",
            "dataType": "TIMESTAMP",
            "default": "CURRENT_TIMESTAMP",
            "option": {
              "autoIncrement": false,
              "primaryKey": false,
              "unique": false,
              "notNull": false
            },
            "ui": {
              "active": false,
              "pk": false,
              "fk": false,
              "pfk": false,
              "widthName": 62.384918212890625,
              "widthComment": 120,
              "widthDataType": 68.2479248046875,
              "widthDefault": 126.42286682128906
            },
            "id": "81bbee9e-0028-49a6-ac47-fb687d66f0d2"
          },
          {
            "name": "view_count",
            "comment": "",
            "dataType": "INT",
            "default": "0",
            "option": {
              "autoIncrement": false,
              "primaryKey": false,
              "unique": false,
              "notNull": true
            },
            "ui": {
              "active": false,
              "pk": false,
              "fk": false,
              "pfk": false,
              "widthName": 62.87892150878906,
              "widthComment": 60,
              "widthDataType": 60,
              "widthDefault": 60
            },
            "id": "c88da518-7249-4ae9-a7ea-01ba5604c120"
          }
        ],
        "ui": {
          "active": false,
          "left": 379,
          "top": 187,
          "zIndex": 3,
          "widthName": 60,
          "widthComment": 60
        },
        "visible": true,
        "id": "6b81fb92-cb8f-4cb7-9a19-b02db78cd190"
      }
    ],
    "indexes": []
  },
  "memo": {
    "memos": []
  },
  "relationship": {
    "relationships": []
  }
}